odoo/addons/web_widget_url_advanced/README.rst
odoo/addons/web_widget_url_advanced/__init__.py
odoo/addons/web_widget_url_advanced/__manifest__.py
odoo/addons/web_widget_url_advanced/i18n/es.po
odoo/addons/web_widget_url_advanced/i18n/it.po
odoo/addons/web_widget_url_advanced/i18n/web_widget_url_advanced.pot
odoo/addons/web_widget_url_advanced/i18n/zh_CN.po
odoo/addons/web_widget_url_advanced/readme/CONTRIBUTORS.md
odoo/addons/web_widget_url_advanced/readme/DESCRIPTION.md
odoo/addons/web_widget_url_advanced/readme/USAGE.md
odoo/addons/web_widget_url_advanced/static/description/after.png
odoo/addons/web_widget_url_advanced/static/description/before.png
odoo/addons/web_widget_url_advanced/static/description/icon.png
odoo/addons/web_widget_url_advanced/static/description/index.html
odoo/addons/web_widget_url_advanced/static/src/fields/url_field.esm.js
odoo/addons/web_widget_url_advanced/static/src/fields/url_field.xml
odoo_addon_web_widget_url_advanced-18.0.1.0.0.3.dist-info/METADATA
odoo_addon_web_widget_url_advanced-18.0.1.0.0.3.dist-info/WHEEL
odoo_addon_web_widget_url_advanced-18.0.1.0.0.3.dist-info/top_level.txt
odoo_addon_web_widget_url_advanced-18.0.1.0.0.3.dist-info/RECORD
